{
    "name": "Saude",
    "id": "shopping",
    "roles": [
        {
            "name":"Aceitar Envio",
            "id": "shipment_accept",
            "services": {
                "distribuidora1": {
                    "name": "ticket de compra",
                    "metadata": {
                        "description": "cria ticket de compra",
                        "user_inputs": [
                            {
                                "name": "id",
                                "description": "Id do usuario que fez a compra"
                            },
                            {
                                "name": "env_id",
                                "description": "The id of the Playground environment"
                            }
                        ]
                    },
                    "action_type": "HTTP",
                    "url": "CONCAT(https://jsonplaceholder.typicode.com/posts/, FIND(user_input.purchase_order_created.id))",
                    "http_method": "GET",
                    "mock": {},
                    "headers": {},
                    "query": {},
                    "form_data": {},
                    "json": {},
                    "output": {}
                }
            }
        }
    ]

}